fake_useragent/__init__.py
fake_useragent/errors.py
fake_useragent/fake.py
fake_useragent/log.py
fake_useragent/settings.py
fake_useragent/utils.py
fake_useragent/data/browsers.json
user_rand_agnt_user-1.8.7.dist-info/AUTHORS
user_rand_agnt_user-1.8.7.dist-info/LICENSE
user_rand_agnt_user-1.8.7.dist-info/METADATA
user_rand_agnt_user-1.8.7.dist-info/WHEEL
user_rand_agnt_user-1.8.7.dist-info/top_level.txt
user_rand_agnt_user-1.8.7.dist-info/RECORD
