Metadata-Version: 2.1
Name: user-rand-agnt-user
Version: 1.8.7
Summary: Agent user generator
Project-URL: Homepage, https://github.com/
Keywords: user,agent,user agent,useragent
Classifier: Development Status :: 5 - Production/Stable
License-File: LICENSE
License-File: AUTHORS
Requires-Dist: importlib-resources >=5.0 ; python_version < "3.10"
Requires-Dist: importlib-metadata ~=4.0 ; python_version < "3.8"
